Syndenv/Syndbox.py
Syndenv/__init__.py
"Syndenv-0.0.1.dist-info/LICENSE,txt"
Syndenv-0.0.1.dist-info/METADATA
Syndenv-0.0.1.dist-info/WHEEL
Syndenv-0.0.1.dist-info/top_level.txt
Syndenv-0.0.1.dist-info/RECORD
