Metadata-Version: 2.1
Name: Syndenv
Version: 0.0.1
Summary: Synthetic Data Environment
Author-email: Radhwane Derraz <derrazradhwane@gmail.com>
Classifier: Programming Language :: Python :: 3
Classifier: License :: OSI Approved :: Apache Software License
Classifier: Operating System :: OS Independent
Requires-Python: >=3.7
License-File: LICENSE,txt
